{"data":{"article":{},"attachments":{},"author_id":"1808933044545630208","conversation_id":"1828550741142688081","created_at":"2024-08-27T22:21:01.000Z","edit_controls":{"edits_remaining":5,"is_edit_eligible":false,"editable_until":"2024-08-27T23:21:01.000Z"},"edit_history_tweet_ids":["1828558362638000556"],"entities":{},"geo":{},"id":"1828558362638000556","in_reply_to_user_id":"1808933044545630208","lang":"zh","possibly_sensitive":false,"public_metrics":{"retweet_count":0,"reply_count":0,"like_count":0,"quote_count":0,"bookmark_count":0,"impression_count":0},"referenced_tweets":[{"type":"replied_to","id":"1828552442235003033"}],"reply_settings":"everyone","text":"虽然干涉了死亡只会让我受更多的苦，但我总不能说给我希望的那些是有错的。\n不敢拼也不敢逃就是这个下场"},"includes":{"users":[{"created_at":"2024-07-04T18:37:10.000Z","description":"只是一些无关紧要的自言自语罢了 炽在水洼中的倒影","id":"1808933044545630208","name":"Pale Fire","profile_image_url":"https://pbs.twimg.com/profile_images/1821650209182486528/1jInQ_wf_normal.jpg","protected":false,"public_metrics":{"followers_count":2,"following_count":3,"tweet_count":24,"listed_count":0,"like_count":12},"username":"TauCeti_10700","verified":false}],"tweets":[{"article":{},"attachments":{},"author_id":"1808933044545630208","conversation_id":"1828550741142688081","created_at":"2024-08-27T22:21:01.000Z","edit_controls":{"edits_remaining":5,"is_edit_eligible":false,"editable_until":"2024-08-27T23:21:01.000Z"},"edit_history_tweet_ids":["1828558362638000556"],"entities":{},"geo":{},"id":"1828558362638000556","in_reply_to_user_id":"1808933044545630208","lang":"zh","possibly_sensitive":false,"public_metrics":{"retweet_count":0,"reply_count":0,"like_count":0,"quote_count":0,"bookmark_count":0,"impression_count":0},"referenced_tweets":[{"type":"replied_to","id":"1828552442235003033"}],"reply_settings":"everyone","text":"虽然干涉了死亡只会让我受更多的苦，但我总不能说给我希望的那些是有错的。\n不敢拼也不敢逃就是这个下场"},{"article":{},"attachments":{},"author_id":"1808933044545630208","conversation_id":"1828550741142688081","created_at":"2024-08-27T21:57:29.000Z","edit_controls":{"edits_remaining":5,"is_edit_eligible":false,"editable_until":"2024-08-27T22:57:29.000Z"},"edit_history_tweet_ids":["1828552442235003033"],"entities":{},"geo":{},"id":"1828552442235003033","in_reply_to_user_id":"1808933044545630208","lang":"zh","possibly_sensitive":false,"public_metrics":{"retweet_count":0,"reply_count":1,"like_count":0,"quote_count":0,"bookmark_count":0,"impression_count":9},"referenced_tweets":[{"type":"replied_to","id":"1828550741142688081"}],"reply_settings":"everyone","text":"好想猫猫，这样的念头会增加“能存活至今真是太好了”，但这真的是正确的吗。只要还有意识就会被自己的思维毒害什么的根本就是事实，药物也改变不了什么。意义这种事我根本就不在乎啦，胆小到连逃避的决定也要逃避而已"}]}}
