{"data":{"article":{},"attachments":{},"author_id":"1808933044545630208","conversation_id":"1920567554826719303","created_at":"2025-05-08T19:52:42.000Z","edit_controls":{"edits_remaining":5,"is_edit_eligible":true,"editable_until":"2025-05-08T20:52:42.000Z"},"edit_history_tweet_ids":["1920567554826719303"],"entities":{},"geo":{},"id":"1920567554826719303","lang":"zh","note_tweet":{"entities":{}},"possibly_sensitive":false,"public_metrics":{"retweet_count":0,"reply_count":0,"like_count":0,"quote_count":0,"bookmark_count":0,"impression_count":0},"reply_settings":"everyone","text":"好无力。我不可能总是完美解决所有事情..但又没有抽身而出的勇气，就这样用软弱折磨自己\n明明没有做错过什么，为什么要这样不安"},"includes":{"users":[{"created_at":"2024-07-04T18:37:10.000Z","description":"只是一些无关紧要的自言自语罢了 炽在水洼中的倒影，因为星光获得了生命 /Per aspera ad astra.","id":"1808933044545630208","location":"0°00′N 260°00′E Mars","name":"Pale Fire","profile_image_url":"https://pbs.twimg.com/profile_images/1853163363142115328/S5o_Yawf_normal.jpg","protected":false,"public_metrics":{"followers_count":49,"following_count":24,"tweet_count":113,"listed_count":0,"like_count":123,"media_count":26},"username":"TauCeti_10700","verified":false}],"tweets":[{"article":{},"attachments":{},"author_id":"1808933044545630208","conversation_id":"1920567554826719303","created_at":"2025-05-08T19:52:42.000Z","edit_controls":{"edits_remaining":5,"is_edit_eligible":true,"editable_until":"2025-05-08T20:52:42.000Z"},"edit_history_tweet_ids":["1920567554826719303"],"entities":{},"geo":{},"id":"1920567554826719303","lang":"zh","note_tweet":{"entities":{}},"possibly_sensitive":false,"public_metrics":{"retweet_count":0,"reply_count":0,"like_count":0,"quote_count":0,"bookmark_count":0,"impression_count":0},"reply_settings":"everyone","text":"好无力。我不可能总是完美解决所有事情..但又没有抽身而出的勇气，就这样用软弱折磨自己\n明明没有做错过什么，为什么要这样不安"}]}}
