{"data":{"article":{},"attachments":{"media_keys":["3_2011870271284920322"],"media_source_tweet_id":["2011870516827865580"]},"author_id":"1808933044545630208","context_annotations":[{"domain":{"id":"46","name":"Business Taxonomy","description":"Categories within Brand Verticals that narrow down the scope of Brands"},"entity":{"id":"1557696940178935808","name":"Gaming Business","description":"Brands, companies, advertisers and every non-person handle with the profit intent related to offline and online games such as gaming consoles, tabletop games, video game publishers"}}],"conversation_id":"2012544755368886451","created_at":"2026-01-17T15:17:15.000Z","edit_controls":{"edits_remaining":5,"is_edit_eligible":false,"editable_until":"2026-01-17T16:17:15.000Z"},"edit_history_tweet_ids":["2012544755368886451"],"entities":{"mentions":[{"start":3,"end":19,"username":"SadButTrueDog02","id":"1287655187100901379"}],"urls":[{"start":62,"end":85,"url":"https://t.co/70rAs3EYQx","expanded_url":"https://x.com/SadButTrueDog02/status/2011870516827865580/photo/1","display_url":"pic.x.com/70rAs3EYQx","media_key":"3_2011870271284920322"}]},"geo":{},"id":"2012544755368886451","lang":"en","note_tweet":{"entities":{}},"possibly_sensitive":false,"public_metrics":{"retweet_count":2746,"reply_count":0,"like_count":0,"quote_count":0,"bookmark_count":0,"impression_count":0},"referenced_tweets":[{"type":"retweeted","id":"2011870516827865580"}],"reply_settings":"everyone","text":"RT @SadButTrueDog02: choose life choose a job choose a career https://t.co/70rAs3EYQx"},"includes":{"media":[{"height":2900,"media_key":"3_2011870271284920322","public_metrics":{},"type":"photo","url":"https://pbs.twimg.com/media/G-uZWjYbQAIiofW.jpg","width":2938}],"users":[{"created_at":"2024-07-04T18:37:10.000Z","description":"穿越语言的壳，任思维溢出容器——请听，离群者无法永恒的悲歌。炽在水洼中的倒影，因为星光获得了生命 /Per aspera ad astra.","id":"1808933044545630208","location":"0°00′N 260°00′E Mars","name":"Pale Fire","profile_image_url":"https://pbs.twimg.com/profile_images/1853163363142115328/S5o_Yawf_normal.jpg","protected":false,"public_metrics":{"followers_count":73,"following_count":45,"tweet_count":330,"listed_count":1,"like_count":368,"media_count":82},"username":"TauCeti_10700","verified":false},{"created_at":"2020-07-27T07:45:26.000Z","description":"телега - рубль.png\n\n🫀📿🃏","entities":{"url":{"urls":[{"start":0,"end":23,"url":"https://t.co/oKLyExsmWV","expanded_url":"https://t.me/rublepng","display_url":"t.me/rublepng"}]}},"id":"1287655187100901379","location":"🇷🇺Санкт-Петербург, Россия","name":"ruble.png🔪","pinned_tweet_id":"2011870516827865580","profile_image_url":"https://pbs.twimg.com/profile_images/1899608585031577600/cPVbVLl8_normal.jpg","protected":false,"public_metrics":{"followers_count":6696,"following_count":171,"tweet_count":1036,"listed_count":24,"like_count":2734,"media_count":99},"url":"https://t.co/oKLyExsmWV","username":"SadButTrueDog02","verified":false}],"tweets":[{"article":{},"attachments":{"media_keys":["3_2011870271284920322"],"media_source_tweet_id":["2011870516827865580"]},"author_id":"1808933044545630208","context_annotations":[{"domain":{"id":"46","name":"Business Taxonomy","description":"Categories within Brand Verticals that narrow down the scope of Brands"},"entity":{"id":"1557696940178935808","name":"Gaming Business","description":"Brands, companies, advertisers and every non-person handle with the profit intent related to offline and online games such as gaming consoles, tabletop games, video game publishers"}}],"conversation_id":"2012544755368886451","created_at":"2026-01-17T15:17:15.000Z","edit_controls":{"edits_remaining":5,"is_edit_eligible":false,"editable_until":"2026-01-17T16:17:15.000Z"},"edit_history_tweet_ids":["2012544755368886451"],"entities":{"mentions":[{"start":3,"end":19,"username":"SadButTrueDog02","id":"1287655187100901379"}],"urls":[{"start":62,"end":85,"url":"https://t.co/70rAs3EYQx","expanded_url":"https://x.com/SadButTrueDog02/status/2011870516827865580/photo/1","display_url":"pic.x.com/70rAs3EYQx","media_key":"3_2011870271284920322"}]},"geo":{},"id":"2012544755368886451","lang":"en","note_tweet":{"entities":{}},"possibly_sensitive":false,"public_metrics":{"retweet_count":2746,"reply_count":0,"like_count":0,"quote_count":0,"bookmark_count":0,"impression_count":0},"referenced_tweets":[{"type":"retweeted","id":"2011870516827865580"}],"reply_settings":"everyone","text":"RT @SadButTrueDog02: choose life choose a job choose a career https://t.co/70rAs3EYQx"},{"article":{},"attachments":{"media_keys":["3_2011870271284920322"]},"author_id":"1287655187100901379","context_annotations":[{"domain":{"id":"46","name":"Business Taxonomy","description":"Categories within Brand Verticals that narrow down the scope of Brands"},"entity":{"id":"1557696940178935808","name":"Gaming Business","description":"Brands, companies, advertisers and every non-person handle with the profit intent related to offline and online games such as gaming consoles, tabletop games, video game publishers"}}],"conversation_id":"2011870516827865580","created_at":"2026-01-15T18:38:04.000Z","edit_controls":{"edits_remaining":5,"is_edit_eligible":false,"editable_until":"2026-01-15T19:38:04.000Z"},"edit_history_tweet_ids":["2011870516827865580"],"entities":{"urls":[{"start":41,"end":64,"url":"https://t.co/70rAs3EYQx","expanded_url":"https://x.com/SadButTrueDog02/status/2011870516827865580/photo/1","display_url":"pic.x.com/70rAs3EYQx","media_key":"3_2011870271284920322"}]},"geo":{},"id":"2011870516827865580","lang":"en","note_tweet":{"entities":{}},"possibly_sensitive":false,"public_metrics":{"retweet_count":2746,"reply_count":24,"like_count":30286,"quote_count":52,"bookmark_count":3769,"impression_count":244130},"reply_settings":"everyone","text":"choose life choose a job choose a career https://t.co/70rAs3EYQx"}]}}
